satkbl/__init__.py
satkbl/ctx.py
satkbl/req.py
satkbl/scratch.py
satkbl/test_util.py
satkbl/util.py
satkbl-0.1.5.dist-info/METADATA
satkbl-0.1.5.dist-info/WHEEL
satkbl-0.1.5.dist-info/licenses/LICENSE
satkbl-0.1.5.dist-info/RECORD
