Metadata-Version: 2.4
Name: satkbl
Version: 0.1.5
Summary: Baselayer for use within the satk ecosystem
License-File: LICENSE
Requires-Python: >=3.13
Requires-Dist: requests>=2.32.5
